<protocol>
    <name>UW Gyn/Pelvis</name>
    <ct>
        <protocol institution="Johnson Creek">8.1 XRT PELVIS</protocol>
        <protocol institution="East">8.2 Pelvis without contrast 0.8sec</protocol>
        <protocol institution="UWHC">XRT_PELVIS</protocol>
    </ct>
    <institutions>
        <institution>UWHC</institution>
        <institution>East</institution>
        <institution>Johnson Creek</institution>
    </institutions>
    <diagnoses>
    </diagnoses>
    <prescription>
        <roi>
            <name>PTV_p></name>
            <type>DX</type>
            <volume units="%">50</volume>
            <dose units="Gy" idl="100"></dose>
        </roi>
        <fractions></fractions>
        <frequency default="true">Daily</frequency>
        <frequency>Twice daily</frequency>
        <imaging>Daily CBCT</imaging>
        <imaging>Weekly kV</imaging>
        <technique modality="Photons" technique="VMAT" code="VMA" machine="TrueBeam">VMAT</technique>
        <technique modality="Photons" technique="Conformal" code="3DC" machine="TrueBeam" default="true">3DCRT
        </technique>
    </prescription>
    <order>
        <name>Pelvis</name>
        <prefix>Pelv_</prefix>
    </order>
    <order>
        <name>Vulva</name>
        <prefix>Vulv_</prefix>
        <prescription>
            <roi>
                <name>PTV_p</name>
                <type>DX</type>
                <volume units="%">50</volume>
                <dose units="Gy" idl="100"></dose>
            </roi>
        </prescription>
        <goals>
            <roi>
                <name>PTV_p</name>
                <type dir="ge">VX</type>
                <volume units="%">50</volume>
                <dose units="%" roi="PTV_p">100</dose>
                <priority>2</priority>
            </roi>
        </goals>
    </order>
    <order>
        <name>Endometrium</name>
        <prefix>Endo_</prefix>
    </order>
    <order>
        <name>Cervix</name>
        <prefix>Cerv_</prefix>
    </order>
    <order>
        <name>Uterus</name>
        <prefix>Uter_</prefix>
    </order>
    <order>
        <name>Vagina</name>
        <prefix>Vagi_</prefix>
    </order>
    <goals>
        <roi>
            <name>Bag_Bowel</name>
            <type>Max</type>
            <volume units="cc">1</volume>
            <dose units="Gy">52</dose>
            <priority>1</priority>
        </roi>
        <roi>
            <name>Bag_Bowel</name>
            <type dir="lt">VX</type>
            <volume units="%">30</volume>
            <dose units="Gy">40</dose>
            <priority>5</priority>
        </roi>
        <roi>
            <name>Bag_Bowel</name>
            <type dir="lt">VX</type>
            <volume units="%">20</volume>
            <dose units="Gy">40</dose>
            <priority>3</priority>
        </roi>
        <roi>
            <name>PTV_p</name>
            <type>Mean</type>
            <volume units="%">50</volume>
            <dose units="%" roi="PTV_p>">100</dose>
            <priority>2</priority>
        </roi>
        <roi>
            <name>PTV_p</name>
            <type dir="lt">VX</type>
            <volume units="cc">0.1</volume>
            <dose units="%" roi="PTV_p>">105</dose>
            <priority>2</priority>
        </roi>
        <roi>
            <name>Rectum</name>
            <type dir="lt">VX</type>
            <volume units="%">60</volume>
            <dose units="Gy">40</dose>
            <priority>3</priority>
        </roi>
        <roi>
            <name>Rectum</name>
            <type dir="lt">VX</type>
            <volume units="%">80</volume>
            <dose units="Gy">40</dose>
            <priority>1</priority>
        </roi>

        <roi>
            <name>Femur_Head_L</name>
            <type dir="lt">VX</type>
            <volume units="%">20</volume>
            <dose units="Gy">30</dose>
            <priority>3</priority>
        </roi>
        <roi>
            <name>Femur_Head_L</name>
            <type dir="lt">VX</type>
            <volume units="%">25</volume>
            <dose units="Gy">30</dose>
            <priority>1</priority>
        </roi>
        <roi>
            <name>Femur_Head_R</name>
            <type dir="lt">VX</type>
            <volume units="%">20</volume>
            <dose units="Gy">30</dose>
            <priority>3</priority>
        </roi>
        <roi>
            <name>Femur_Head_R</name>
            <type dir="lt">VX</type>
            <volume units="%">25</volume>
            <dose units="Gy">30</dose>
            <priority>1</priority>
        </roi>
        <roi>
            <name>Bone_Marrow</name>
            <type dir="lt">VX</type>
            <volume units="%">80</volume>
            <dose units="Gy">10</dose>
            <priority>3</priority>
        </roi>
        <roi>
            <name>Bone_Marrow</name>
            <type dir="lt">VX</type>
            <volume units="%">70</volume>
            <dose units="Gy">20</dose>
            <priority>3</priority>
        </roi>
        <roi>
            <name>Bone_Marrow</name>
            <type dir="lt">VX</type>
            <volume units="%">90</volume>
            <dose units="Gy">10</dose>
            <priority>1</priority>
        </roi>
        <roi>
            <name>Bone_Marrow</name>
            <type dir="lt">VX</type>
            <volume units="%">75</volume>
            <dose units="Gy">20</dose>
            <priority>1</priority>
        </roi>
        <roi>
            <name>Bladder</name>
            <type dir="lt">VX</type>
            <volume units="%">30</volume>
            <dose units="Gy">45</dose>
            <priority>3</priority>
        </roi>
        <roi>
            <name>Bladder</name>
            <type dir="lt">VX</type>
            <volume units="%">10</volume>
            <dose units="Gy">50</dose>
            <priority>3</priority>
        </roi>
        <roi>
            <name>Bladder</name>
            <type dir="lt">VX</type>
            <volume units="%">40</volume>
            <dose units="Gy">45</dose>
            <priority>1</priority>
        </roi>
        <roi>
            <name>SpinalCord</name>
            <type>Max</type>
            <volume units="cc">0.01</volume>
            <dose units="Gy">45</dose>
            <priority>3</priority>
        </roi>
        <roi>
            <name>SpinalCord</name>
            <type>Max</type>
            <volume units="cc">0.01</volume>
            <dose units="Gy">50</dose>
            <priority>1</priority>
        </roi>
        <roi>
            <name>CaudaEquina</name>
            <type>Max</type>
            <volume units="cc">0.01</volume>
            <dose units="Gy">45</dose>
            <priority>3</priority>
        </roi>
        <roi>
            <name>CaudaEquina</name>
            <type>Max</type>
            <volume units="cc">0.01</volume>
            <dose units="Gy">50</dose>
            <priority>1</priority>
        </roi>
        <roi>
            <name>Kidney_L</name>
            <type dir="lt">VX</type>
            <volume units="%">50</volume>
            <dose units="Gy">12</dose>
            <priority>3</priority>
        </roi>
        <roi>
            <name>Kidney_L</name>
            <type dir="lt">VX</type>
            <volume units="%">30</volume>
            <dose units="Gy">20</dose>
            <priority>3</priority>
        </roi>
        <roi>
            <name>Kidney_L</name>
            <type dir="lt">Mean</type>
            <dose units="Gy">15</dose>
            <priority>1</priority>
        </roi>
        <roi>
            <name>Kidney_L</name>
            <type dir="lt">VX</type>
            <volume units="%">55</volume>
            <dose units="Gy">12</dose>
            <priority>1</priority>
        </roi>
        <roi>
            <name>Kidney_R</name>
            <type dir="lt">VX</type>
            <volume units="%">50</volume>
            <dose units="Gy">12</dose>
            <priority>3</priority>
        </roi>
        <roi>
            <name>Kidney_R</name>
            <type dir="lt">VX</type>
            <volume units="%">30</volume>
            <dose units="Gy">20</dose>
            <priority>3</priority>
        </roi>
        <roi>
            <name>Kidney_R</name>
            <type dir="lt">Mean</type>
            <dose units="Gy">15</dose>
            <priority>1</priority>
        </roi>
        <roi>
            <name>Kidney_R</name>
            <type dir="lt">VX</type>
            <volume units="%">55</volume>
            <dose units="Gy">12</dose>
            <priority>1</priority>
        </roi>
        <goalset>
            <name>QUANTEC</name>
            <priority>5</priority>
        </goalset>
    </goals>
</protocol>
